amistock/__init__.py
amistock/api.py
amistock/utils.py
amistock-0.6.1.dist-info/LICENSE
amistock-0.6.1.dist-info/METADATA
amistock-0.6.1.dist-info/WHEEL
amistock-0.6.1.dist-info/top_level.txt
amistock-0.6.1.dist-info/RECORD
