Metadata-Version: 2.1
Name: amistock
Version: 0.6.1
Summary: Python module to interact with stock data via Django API
Home-page: https://github.com/amistock/amistock
Author: Ami Stock
Author-email: amistockpro@gmail.com
License: UNKNOWN
Platform: UNKNOWN
Classifier: Programming Language :: Python :: 3
Classifier: License :: OSI Approved :: MIT License
Classifier: Operating System :: OS Independent
Requires-Python: >=3.6
Requires-Dist: requests
